Workbook

Sheet Тест_в2
B1: Тест помогает определить ваш стиль человекоцентричного лидерства — то, как вы создаёте осмысленную, тёплую и результативную рабочую среду для команды. Каждый лидер реализует её по‑своему — через один из четырёх стилей, которые опираются на векторы модели: Культура, Лидер, Процессы и практики, Стратегия. Тест расскажет больше о вашем ведущем стиле человекоцентричного лидерства и его особенностях. Опросник не направлен на оценку уровня\индекса человекоцентричности и не оценивает качество вашего лидерства. Тест поможет: - Узнать, какой стиль человекоцентричного лидерства вам ближе и как он проявляется в вашей работе. - Понять, в каких ситуациях ваш стиль наиболее эффективен, а где стоит использовать другие подходы. - Получить рекомендации по развитию вашего стиля, чтобы усилить влияние на команду и компанию. По итогам теста вы получите персонализированный отчёт. Почему результатам можно верить? Тест разработан командой сертифицированных асессоров "Ростелекома" на базе: - Модели человекоцентричного лидерства в "Ростелекоме" - Классической двухфакторой модели руководства Ренсиса Лайкерта ("Фокус на людей" и "Фокус на задачи") - Теории контекстов взаимодействия в команде Рэймонда Белбина
B2: Как работать с тестом? Вам будет предложено 14 блоков. В каждом из блоков распределите 7 баллов между 4 вариантами. Каждому из вариантов можно присвоить от 0 до 7 баллов. Чем больше баллов вы присваиваете варианту, тем точнее он описывает ваше обычное поведение. Одному утверждению можно отдать все 7 баллов.
B3: Рекомендации по заполнению: Следите за подсказками, они помогут верно распределить баллы. Если какой-то из блоков будет пропущен или превышено\не хватает баллов по блоку, система предложит к нему вернуться. В конце теста вы получите отчёт, в котором будет информация о вашем ведущем стиле человекоцентричного лидерства, его особенностях, и рекомендации, как повысить человекоцентричность в вашей команде . Также в отчёте вы сможете познакомиться с другими стилями. Обратите внимание, в тесте нет правильных или неправильных вариантов. Постарайтесь отвечать открыто и честно, не раздумывая долго. Тест не ограничен по времени.
B7: Тест | C7: Распределите 7 баллов между 4 вариантами. Каждому из вариантов можно присвоить от 0 до 7 баллов. Чем больше баллов вы присваиваете варианту, тем точнее он описывает ваше обычное поведение. Одному утверждению можно отдать все 7 баллов. | D7: При заполнении пользователем ячейки с баллами, подсвечивается кол-во оставшихся баллов из 7. Если все 7 баллов использованы – всплывает сообщение «Вы использовали все баллы». | E7: Ключ для проектной команды
B8: блок 1/1 вклад в команду (что я привношу) | D8: для проектной команды, не выводим для пользователя
A9: 1 | B9: В чем состоит ваш вклад в работу команды? | D9: =IF(SUM(C10:C13)>7, "Вы использовали все баллы", IF(SUM(C10:C13)<7, "Вы использовали не все баллы", ""))
A10: a | B10: Я задаю амбициозные цели и помогаю команде создавать результат, приносящий ценность клиенту и обществу | C10: 3 | D10: ="Осталось: "&7-SUM(C10:C13)&" из 7" -> Осталось: 0 из 7 | E10: Целеустремленный
A11: b | B11: Я создаю и поддерживаю в команде атмосферу взаимопомощи, уважения и доброжелательного общения | E11: Командный
A12: c | B12: Я создаю условия для развития и раскрытия потенциала сотрудников, мотивирую сотрудников | C12: 1 | E12: Вдохновляющий
A13: d | B13: Я выстраиваю понятные и прозрачные процессы для работы, фиксирую ключевые договоренности | C13: 3 | E13: Процессный
B14: блок 2\1 (мои ограничения как члена команды, теневая сторона) | D14: для проектной команды, не выводим для пользователя
A15: 2 | B15: Какие у вас недостатки как у лидера? | D15: =IF(SUM(C16:C19)>7, "Вы использовали все баллы", IF(SUM(C16:C19)<7, "Вы использовали не все баллы", ""))
A16: a | B16: Я могу настаивать на соблюдении договорённостей и ясности правил, даже когда ситуация требует гибкости | C16: 3 | D16: ="Осталось: "&7-SUM(C16:C19)&" из 7" -> Осталось: 0 из 7 | E16: Процессный
A17: b | B17: Я могу быть требовательным к срокам и результатам для клиента и компании, уделяя недостаточно внимания состоянию подчиненных | C17: 3 | E17: Целеустремленный
A18: c | B18: Я могу больше фокусироваться на атмосфере в команде и откладывать жесткие, но необходимые кадровые решения | E18: Командный
A19: d | B19: Я могу много времени уделять развитию людей и вдохновению, и ослаблять контроль за результатами | C19: 1 | E19: Вдохновляющий
B20: блок 3\1 (работа с другими, стиль взаимодействия) | D20: для проектной команды, не выводим для пользователя
A21: 3 | B21: В чём ваша ключевая роль, когда дело касается коммуникаций в команде и совместных задач? | D21: =IF(SUM(C22:C25)>7, "Вы использовали все баллы", IF(SUM(C22:C25)<7, "Вы использовали не все баллы", ""))
A22: a | B22: Я внимательно слушаю, поддерживаю уважительный диалог и доброжелательное общение в команде | D22: ="Осталось: "&7-SUM(C22:C25)&" из 7" -> Осталось: 0 из 7 | E22: Командный
A23: b | B23: Я транслирую связь задач с ценностью для клиента и общества, помогая команде прийти к лучшему результату | C23: 3 | E23: Целеустремленный
A24: c | B24: Я объясняю, как устроена работа в проекте, чтобы каждый понимал свою роль, договорённости и следующий шаг | C24: 3 | E24: Процессный
A25: d | B25: Я показываю команде, как выполнение текущей задачи развивает их компетенции и открывает новые возможности | C25: 1 | E25: Вдохновляющий
B26: блок 4\1 (отношение к задачам, как я подхожу к работе) | D26: для проектной команды, не выводим для пользователя
A27: 4 | B27: Каковы особенности вашего лидерского стиля в привычных рабочих процессах? | D27: =IF(SUM(C28:C31)>7, "Вы использовали все баллы", IF(SUM(C28:C31)<7, "Вы использовали не все баллы", ""))
A28: a | B28: Я задаю пример стремления к развитию и создаю условия для освоения новых компетенций другими | D28: ="Осталось: "&7-SUM(C28:C31)&" из 7" -> Осталось: 0 из 7 | E28: Вдохновляющий
A29: b | B29: Я систематизирую задачи и выстраиваю четкие алгоритмы, чтобы команда работала по прозрачным процессам | C29: 3 | E29: Процессный
A30: c | B30: Я контролирую ключевые показатели, четко слежу за достижением результата | C30: 3 | E30: Целеустремленный
A31: d | B31: Я распределяю задачи, чтобы каждый чувствовал свою значимость, и поощряю взаимовыручку в команде | C31: 1 | E31: Командный
B32: блок 5\1 (личное удовлетворение, что мне нравится в работе) | D32: для проектной команды, не выводим для пользователя
A33: 5 | B33: Что вдохновляет вас как лидера? | D33: =IF(SUM(C34:C37)>7, "Вы использовали все баллы", IF(SUM(C34:C37)<7, "Вы использовали не все баллы", ""))
A34: a | B34: Видеть, что в команде вежливо общаются и готовы помогать друг другу | D34: ="Осталось: "&7-SUM(C34:C37)&" из 7" -> Осталось: 0 из 7 | E34: Командный
A35: b | B35: Замечать, что люди раскрывают потенциал, осваивают новое и берутся за развивающие задачи | C35: 1 | E35: Вдохновляющий
A36: c | B36: Видеть, как отлаженная мною система работает как часы | C36: 3 | E36: Процессный
A37: d | B37: Видеть, как моя команда достигает амбициозных целей, которые приносят реальную пользу клиентам и заказчикам | C37: 3 | E37: Целеустремленный
B38: блок 6\1 (отношение к другим, коллаборация) | D38: для проектной команды, не выводим для пользователя
A39: 6 | B39: Как вы вкладываетесь в развитие идей других коллег? | D39: =IF(SUM(C40:C43)>7, "Вы использовали все баллы", IF(SUM(C40:C43)<7, "Вы использовали не все баллы", ""))
A40: a | B40: Я продвигаю идеи коллег, создавая для них возможности развития | D40: ="Осталось: "&7-SUM(C40:C43)&" из 7" -> Осталось: 0 из 7 | E40: Вдохновляющий
A41: b | B41: Я проверяю идеи на соответствие принятым стандартам и реализуемость | C41: 3 | E41: Процессный
A42: c | B42: Я помогаю оценить идеи по их вкладу в прибыль\KPI и пользу для Общества | C42: 3 | E42: Целеустремленный
A43: d | B43: Я создаю благоприятную атмосферу для открытого обсуждения идей в команде | C43: 1 | E43: Командный
B44: блок 7\1 (финализация, результативность) | D44: для проектной команды, не выводим для пользователя
A45: 7 | B45: На чём вы делаете фокус, когда задача уже реализована? | D45: =IF(SUM(C46:C49)>7, "Вы использовали все баллы", IF(SUM(C46:C49)<7, "Вы использовали не все баллы", ""))
A46: a | B46: Анализирую качество выполнения задачи и то, какую ценность для клиента приносит результат | C46: 3 | D46: ="Осталось: "&7-SUM(C46:C49)&" из 7" -> Осталось: 0 из 7 | E46: Целеустремленный
A47: b | B47: Делаю ретроспективу с командой, обсуждаю, как мы вместе можем усилиться | C47: 1 | E47: Командный
A48: c | B48: Обсуждаю с командой достигнутые результаты, мотивируя и вдохновляя на новые достижения | E48: Вдохновляющий
A49: d | B49: Провожу аудит процессов (с которыми столкнулся), чтобы сделать их оптимальными | C49: 3 | E49: Процессный
B50: блок 1/2 вклад в команду (что я привношу) | D50: для проектной команды, не выводим для пользователя
A51: 8 | B51: В чем проявляется ваша ценность, когда команда приступает к новой задаче? | D51: =IF(SUM(C52:C55)>7, "Вы использовали все баллы", IF(SUM(C52:C55)<7, "Вы использовали не все баллы", ""))
A52: a | B52: Помогаю участникам услышать друг друга и договориться о совместной работе | D52: ="Осталось: "&7-SUM(C52:C55)&" из 7" -> Осталось: 0 из 7 | E52: Командный
A53: b | B53: Помогаю сотрудникам увидеть возможности для развития и поддерживаю инициативу | C53: 1 | E53: Вдохновляющий
A54: c | B54: Проясняю роли, договоренности и порядок совместной работы | C54: 3 | E54: Процессный
A55: d | B55: Я помогаю прояснить образ результата в задаче и какую ценность для клиентов принесет результат | C55: 3 | E55: Целеустремленный
B56: блок 2\2 (мои ограничения как члена команды, теневая сторона) | D56: для проектной команды, не выводим для пользователя
A57: 9 | B57: Что окружающие прощают вам как лидеру? | D57: =IF(SUM(C58:C61)>7, "Вы использовали все баллы", IF(SUM(C58:C61)<7, "Вы использовали не все баллы", ""))
A58: a | B58: Излишнюю мягкость, так как я создаю комфортную среду для командной работы | D58: ="Осталось: "&7-SUM(C58:C61)&" из 7" -> Осталось: 0 из 7 | E58: Командный
A59: b | B59: Эмоциональность, так как мне важно вдохновить других | C59: 1 | E59: Вдохновляющий
A60: c | B60: Принципиальность в следовании правилам, так как я обеспечиваю прозрачную и предсказуемую среду для команды | C60: 3 | E60: Процессный
A61: d | B61: Жесткость в некоторых ситуациях, так как я сосредоточен на создании ценности для заказчиков и клиентов | C61: 3 | E61: Целеустремленный
B62: блок 3\2 (работа с другими, стиль взаимодействия) | D62: для проектной команды, не выводим для пользователя
A63: 10 | B63: При возникновении конфликтов в общих задачах вы чаще? | D63: =IF(SUM(C64:C67)>7, "Вы использовали все баллы", IF(SUM(C64:C67)<7, "Вы использовали не все баллы", ""))
A64: a | B64: Помогаю команде увидеть в разногласиях точку для роста и поиска новых решений | D64: ="Осталось: "&7-SUM(C64:C67)&" из 7" -> Осталось: 0 из 7 | E64: Вдохновляющий
A65: b | B65: Проясняю предмет разногласия и корректирую процесс так, чтобы проблема не повторилась | C65: 3 | E65: Процессный
A66: c | B66: Возвращаю обсуждение к общей цели, фактам, потребностям клиента, чтобы быстрее двигаться дальше | C66: 3 | E66: Целеустремленный
A67: d | B67: Становлюсь медиатором, чтобы помочь коллегам договориться о командной работе | C67: 1 | E67: Командный
B68: блок 4\2(отношение к задачам, как я подхожу к работе) | D68: для проектной команды, не выводим для пользователя
A69: 11 | B69: Как вы обычно действуете, когда понимаете, что команда отклоняется от цели? | D69: =IF(SUM(C70:C73)>7, "Вы использовали все баллы", IF(SUM(C70:C73)<7, "Вы использовали не все баллы", ""))
A70: a | B70: Я помогаю команде сфокусироваться на главном и направляю наши усилия на то, чтобы цели были достигнуты в срок, несмотря на возникшие сложности | C70: 3 | D70: ="Осталось: "&7-SUM(C70:C73)&" из 7" -> Осталось: 0 из 7 | E70: Целеустремленный
A71: b | B71: Я собираю команду для открытого обсуждения проблем, чтобы снять эмоциональное напряжение и вместе обсудить возникшие трудности | C71: 1 | E71: Командный
A72: c | B72: Я вдохновляю команду на поиск нестандартных решений и своим примером показываю, как преодолеть возникшие трудности | E72: Вдохновляющий
A73: d | B73: Я ищу "узкие места", которые привели к ошибке, чтобы устранить их и избежать их повторения | C73: 3 | E73: Процессный
B74: блок 5\2 (личное удовлетворение, что мне нравится в работе) | D74: для проектной команды, не выводим для пользователя
A75: 12 | B75: Что вас больше всего мотивирует в работе? | D75: =IF(SUM(C76:C79)>7, "Вы использовали все баллы", IF(SUM(C76:C79)<7, "Вы использовали не все баллы", ""))
A76: a | B76: Доброжелательный микроклимат в команде | D76: ="Осталось: "&7-SUM(C76:C79)&" из 7" -> Осталось: 0 из 7 | E76: Командный
A77: b | B77: Достижение амбициозных результатов, превышающих ожидания клиентов и Компании | C77: 3 | E77: Целеустремленный
A78: c | B78: Порядок и предсказуемость в рабочих процессах | C78: 3 | E78: Процессный
A79: d | B79: Рост и развитие сотрудников в команде | C79: 1 | E79: Вдохновляющий
B80: блок 6\2(отношение к другим, коллаборация) | D80: для проектной команды, не выводим для пользователя
A81: 13 | B81: С чего вы начнете обсуждение идеи на рабочей встрече с коллегами, с которыми ранее не взаимодействовали? | D81: =IF(SUM(C82:C85)>7, "Вы использовали все баллы", IF(SUM(C82:C85)<7, "Вы использовали не все баллы", ""))
A82: a | B82: С создания структуры и порядка в групповой работе | C82: 3 | D82: ="Осталось: "&7-SUM(C82:C85)&" из 7" -> Осталось: 0 из 7 | E82: Процессный
A83: b | B83: С анализа проблемы клиента/заказчика и формулирования образа результата | C83: 3 | E83: Целеустремленный
A84: c | B84: С создания благоприятной командной атмосферы и взаимодействии | C84: 1 | E84: Командный
A85: d | B85: С мотивации и вдохновения коллег | E85: Вдохновляющий
B86: блок 7\2(финализация, результативность) | D86: для проектной команды, не выводим для пользователя
A87: 14 | B87: Что для вас наиболее важно в результатах работы вашей команды? | D87: =IF(SUM(C88:C91)>7, "Вы использовали все баллы", IF(SUM(C88:C91)<7, "Вы использовали не все баллы", ""))
A88: a | B88: Публичное признание успеха моей команды как способ поддержать их мотивацию и развитие | D88: ="Осталось: "&7-SUM(C88:C91)&" из 7" -> Осталось: 0 из 7 | E88: Вдохновляющий
A89: b | B89: Создание понятного способа работы, который можно тиражировать в похожих задачах | C89: 3 | E89: Процессный
A90: c | B90: Достижение сверхцелей и всех показателей, которые принесут пользу компании и коллегам | C90: 3 | E90: Целеустремленный
A91: d | B91: Сплоченность и партнерство в команде, в которой не страшно говорить о недочетах | C91: 1 | E91: Командный

Sheet Механика подсчета результатов
A1: 1. | B1: Перемешиваем варианты ответов | J1: 2. | K1: Таблица подсчета результатов | P1: 3. | Q1: Типы профилей Общий подход: Берём максимум и считаем, сколько векторов находятся от него на расстоянии ≤5. 1 вектор (он сам)→ сфокусированный, 2 вектора → двухвекторный, 3 вектора → широкий, 4 вектора → сбалансированный. | S1: 4. | T1: Механика выведения результатов
K2: Целеустремленный | L2: Вдохновляющий | M2: Командный | N2: Процессный | O2: проверка | Q2: Название | R2: Ведущие стили (по наибольшему по сравнению с другими количеству баллов) | T2: Целеустремленный | U2: Вдохновляющий | V2: Командный | W2: Процессный | X2: StyleIdx | Y2: Δ | Z2: Максимум | AA2: В верхней зоне | AB2: Тип профиля | AC2: Код профиля | AD2: Ведущие векторы по убыванию балла | AE2: Проверка суммы | AF2: Логика | AG2: Ключ Ц | AH2: Ключ В | AI2: Ключ К | AJ2: Ключ П | AK2: 1-й вектор | AL2: 2-й вектор | AM2: 3-й вектор | AN2: 4-й вектор
A3: блоки | B3: 1 | C3: A | D3: C | E3: B | F3: D | H3: А- «Целеустременный» | J3: 1 | K3: =IFERROR(VALUE(INDEX(Тест_в2!C10:C13, MATCH("A", C3:F3, 0))), 0) -> 3 | L3: =IFERROR(VALUE(INDEX(Тест_в2!C10:C13, MATCH("B", C3:F3, 0))), 0) -> 1 | M3: =IFERROR(VALUE(INDEX(Тест_в2!C10:C13, MATCH("C", C3:F3, 0))), 0) -> 0 | N3: =IFERROR(VALUE(INDEX(Тест_в2!C10:C13, MATCH("D", C3:F3, 0))), 0) -> 3 | O3: =SUM(K3:N3) -> 7 | Q3: Сфокусированный | R3: Целеустременный | T3: =K17 -> 42 | U3: =L17 -> 7 | V3: =M17 -> 7 | W3: =N17 -> 42 | X3: =MATCH(MAX(T3:W3),T3:W3,0) -> 1 | Y3: 5 | Z3: =MAX(T3:W3) -> 42 | AA3: =COUNTIF(T3:W3,">="&(Z3-Y3)) -> 2 | AB3: =IF(AA3=1,"Сфокусированный",IF(AA3=2,"Двухвекторный",IF(AA3=3,"Широкий",IF(AA3=4,"Сбалансированный","Ошибка")))) -> Двухвекторный | AC3: =IF(T3>=Z3-Y3,1,0)+IF(U3>=Z3-Y3,2,0)+IF(V3>=Z3-Y3,4,0)+IF(W3>=Z3-Y3,8,0) -> 9 | AD3: =IF('[1]Механика подсчета результатов'!$AA$3=1,'[1]Механика подсчета результатов'!$AK$3,IF('[1]Механика подсчета результатов'!$AA$3=2,'[1]Механика подсчета результатов'!$AK$3&" и "&'[1]Механика подсчета результатов'!$AL$3,IF('[1]Механика подсчета результатов'!$AA$3=3,'[1]Механика подсчета результатов'!$AK$3&", "&'[1]Механика подсчета результатов'!$AL$3&", "&'[1]Механика подсчета результатов'!$AM$3,'[1]Механика подсчета результатов'!$AK$3&", "&'[1]Механика подсчета результатов'!$AL$3&", "&'[1]Механика подсчета результатов'!$AM$3&" и "&'[1]Механика подсчета результатов'!$AN$3))) -> Целеустремленный и Процессный | AE3: =IF(SUM(T3:W3)=98,"OK","Проверить сумму") -> OK | AF3: Сравниваем каждый вектор с максимумом. Если разница ≤ Δ, вектор входит в верхнюю зону. 1 вектор = сфокусированный; 2 = двухвекторный; 3 = широкий; 4 = сбалансированный. | AG3: =IF('[1]Механика подсчета результатов'!$T$3>='[1]Механика подсчета результатов'!$Z$3-'[1]Механика подсчета результатов'!$Y$3,'[1]Механика подсчета результатов'!$T$3*10+4,-1) -> 394 | AH3: =IF('[1]Механика подсчета результатов'!$U$3>='[1]Механика подсчета результатов'!$Z$3-'[1]Механика подсчета результатов'!$Y$3,'[1]Механика подсчета результатов'!$U$3*10+3,-1) -> -1 | AI3: =IF('[1]Механика подсчета результатов'!$V$3>='[1]Механика подсчета результатов'!$Z$3-'[1]Механика подсчета результатов'!$Y$3,'[1]Механика подсчета результатов'!$V$3*10+2,-1) -> -1 | AJ3: =IF('[1]Механика подсчета результатов'!$W$3>='[1]Механика подсчета результатов'!$Z$3-'[1]Механика подсчета результатов'!$Y$3,'[1]Механика подсчета результатов'!$W$3*10+1,-1) -> 421 | AK3: =IF('[1]Механика подсчета результатов'!$T$3>='[1]Механика подсчета результатов'!$Z$3-'[1]Механика подсчета результатов'!$Y$3,'[1]Механика подсчета результатов'!$T$2,IF('[1]Механика подсчета результатов'!$U$3>='[1]Механика подсчета результатов'!$Z$3-'[1]Механика подсчета результатов'!$Y$3,'[1]Механика подсчета результатов'!$U$2,IF('[1]Механика подсчета результатов'!$V$3>='[1]Механика подсчета результатов'!$Z$3-'[1]Механика подсчета результатов'!$Y$3,'[1]Механика подсчета результатов'!$V$2,IF('[1]Механика подсчета результатов'!$W$3>='[1]Механика подсчета результатов'!$Z$3-'[1]Механика подсчета результатов'!$Y$3,'[1]Механика подсчета результатов'!$W$2,"")))) -> Целеустремленный | AL3: =IF('[1]Механика подсчета результатов'!$AA$3>=2,IF('[1]Механика подсчета результатов'!$T$3>='[1]Механика подсчета результатов'!$Z$3-'[1]Механика подсчета результатов'!$Y$3,IF('[1]Механика подсчета результатов'!$U$3>='[1]Механика подсчета результатов'!$Z$3-'[1]Механика подсчета результатов'!$Y$3,'[1]Механика подсчета результатов'!$U$2,IF('[1]Механика подсчета результатов'!$V$3>='[1]Механика подсчета результатов'!$Z$3-'[1]Механика подсчета результатов'!$Y$3,'[1]Механика подсчета результатов'!$V$2,IF('[1]Механика подсчета результатов'!$W$3>='[1]Механика подсчета результатов'!$Z$3-'[1]Механика подсчета результатов'!$Y$3,'[1]Механика подсчета результатов'!$W$2,""))),IF('[1]Механика подсчета результатов'!$U$3>='[1]Механика подсчета результатов'!$Z$3-'[1]Механика подсчета результатов'!$Y$3,IF('[1]Механика подсчета результатов'!$V$3>='[1]Механика подсчета результатов'!$Z$3-'[1]Механика подсчета результатов'!$Y$3,'[1]Механика подсчета результатов'!$V$2,IF('[1]Механика подсчета результатов'!$W$3>='[1]Механика подсчета результатов'!$Z$3-'[1]Механика подсчета результатов'!$Y$3,'[1]Механика подсчета результатов'!$W$2,"")),IF('[1]Механика подсчета результатов'!$V$3>='[1]Механика подсчета результатов'!$Z$3-'[1]Механика подсчета результатов'!$Y$3,IF('[1]Механика подсчета результатов'!$W$3>='[1]Механика подсчета результатов'!$Z$3-'[1]Механика подсчета результатов'!$Y$3,'[1]Механика подсчета результатов'!$W$2,""),IF('[1]Механика подсчета результатов'!$W$3>='[1]Механика подсчета результатов'!$Z$3-'[1]Механика подсчета результатов'!$Y$3,'[1]Механика подсчета результатов'!$W$2,"")))),"") -> Процессный | AM3: =IF('[1]Механика подсчета результатов'!$AA$3>=3,IF('[1]Механика подсчета результатов'!$T$3>='[1]Механика подсчета результатов'!$Z$3-'[1]Механика подсчета результатов'!$Y$3,IF('[1]Механика подсчета результатов'!$U$3>='[1]Механика подсчета результатов'!$Z$3-'[1]Механика подсчета результатов'!$Y$3,IF('[1]Механика подсчета результатов'!$V$3>='[1]Механика подсчета результатов'!$Z$3-'[1]Механика подсчета результатов'!$Y$3,'[1]Механика подсчета результатов'!$V$2,IF('[1]Механика подсчета результатов'!$W$3>='[1]Механика подсчета результатов'!$Z$3-'[1]Механика подсчета результатов'!$Y$3,'[1]Механика подсчета результатов'!$W$2,"")),IF('[1]Механика подсчета результатов'!$V$3>='[1]Механика подсчета результатов'!$Z$3-'[1]Механика подсчета результатов'!$Y$3,IF('[1]Механика подсчета результатов'!$W$3>='[1]Механика подсчета результатов'!$Z$3-'[1]Механика подсчета результатов'!$Y$3,'[1]Механика подсчета результатов'!$W$2,""),IF('[1]Механика подсчета результатов'!$W$3>='[1]Механика подсчета результатов'!$Z$3-'[1]Механика подсчета результатов'!$Y$3,'[1]Механика подсчета результатов'!$W$2,""))),IF('[1]Механика подсчета результатов'!$U$3>='[1]Механика подсчета результатов'!$Z$3-'[1]Механика подсчета результатов'!$Y$3,IF('[1]Механика подсчета результатов'!$V$3>='[1]Механика подсчета результатов'!$Z$3-'[1]Механика подсчета результатов'!$Y$3,IF('[1]Механика подсчета результатов'!$W$3>='[1]Механика подсчета результатов'!$Z$3-'[1]Механика подсчета результатов'!$Y$3,'[1]Механика подсчета результатов'!$W$2,""),IF('[1]Механика подсчета результатов'!$W$3>='[1]Механика подсчета результатов'!$Z$3-'[1]Механика подсчета результатов'!$Y$3,'[1]Механика подсчета результатов'!$W$2,"")),IF('[1]Механика подсчета результатов'!$V$3>='[1]Механика подсчета результатов'!$Z$3-'[1]Механика подсчета результатов'!$Y$3,IF('[1]Механика подсчета результатов'!$W$3>='[1]Механика подсчета результатов'!$Z$3-'[1]Механика подсчета результатов'!$Y$3,'[1]Механика подсчета результатов'!$W$2,""),IF('[1]Механика подсчета результатов'!$W$3>='[1]Механика подсчета результатов'!$Z$3-'[1]Механика подсчета результатов'!$Y$3,'[1]Механика подсчета результатов'!$W$2,"")))),"") | AN3: =IF('[1]Механика подсчета результатов'!$AA$3>=4,IF('[1]Механика подсчета результатов'!$T$3>='[1]Механика подсчета результатов'!$Z$3-'[1]Механика подсчета результатов'!$Y$3,IF('[1]Механика подсчета результатов'!$U$3>='[1]Механика подсчета результатов'!$Z$3-'[1]Механика подсчета результатов'!$Y$3,IF('[1]Механика подсчета результатов'!$V$3>='[1]Механика подсчета результатов'!$Z$3-'[1]Механика подсчета результатов'!$Y$3,IF('[1]Механика подсчета результатов'!$W$3>='[1]Механика подсчета результатов'!$Z$3-'[1]Механика подсчета результатов'!$Y$3,'[1]Механика подсчета результатов'!$W$2,""),""),""),""),"") | AO3: =IF('[1]Механика подсчета результатов'!$T$3<('[1]Механика подсчета результатов'!$Z$3-'[1]Механика подсчета результатов'!$Y$3),'[1]Механика подсчета результатов'!$T$3*10+4,-1) -> -1 | AP3: =IF('[1]Механика подсчета результатов'!$U$3<('[1]Механика подсчета результатов'!$Z$3-'[1]Механика подсчета результатов'!$Y$3),'[1]Механика подсчета результатов'!$U$3*10+3,-1) -> 93 | AQ3: =IF('[1]Механика подсчета результатов'!$V$3<('[1]Механика подсчета результатов'!$Z$3-'[1]Механика подсчета результатов'!$Y$3),'[1]Механика подсчета результатов'!$V$3*10+2,-1) -> 82 | AR3: =IF('[1]Механика подсчета результатов'!$W$3<('[1]Механика подсчета результатов'!$Z$3-'[1]Механика подсчета результатов'!$Y$3),'[1]Механика подсчета результатов'!$W$3*10+1,-1) -> -1 | AS3: =IF(1<=(4-'[1]Механика подсчета результатов'!$AA$3),IFERROR(INDEX('[1]Механика подсчета результатов'!$T$2:$W$2,1,MATCH(LARGE('[1]Механика подсчета результатов'!$AO$3:$AR$3,1),'[1]Механика подсчета результатов'!$AO$3:$AR$3,0)),""),"") -> Вдохновляющий | AU3: =IF(2<=(4-'[1]Механика подсчета результатов'!$AA$3),IFERROR(INDEX('[1]Механика подсчета результатов'!$T$2:$W$2,1,MATCH(LARGE('[1]Механика подсчета результатов'!$AO$3:$AR$3,2),'[1]Механика подсчета результатов'!$AO$3:$AR$3,0)),""),"") -> Командный | AW3: =IF(3<=(4-'[1]Механика подсчета результатов'!$AA$3),IFERROR(INDEX('[1]Механика подсчета результатов'!$T$2:$W$2,1,MATCH(LARGE('[1]Механика подсчета результатов'!$AO$3:$AR$3,3),'[1]Механика подсчета результатов'!$AO$3:$AR$3,0)),""),"") | AY3: =IF('[1]Механика подсчета результатов'!$AA$3=1,"Сфокусированный",IF('[1]Механика подсчета результатов'!$AA$3=2,"Двухвекторный профиль",IF('[1]Механика подсчета результатов'!$AA$3=3,"Широкий профиль","Сбалансированный профиль"))) -> Двухвекторный профиль
B4: 2 | C4: D | D4: A | E4: C | F4: B | H4: В- «Вдохновлящий» | J4: 2 | K4: =IFERROR(VALUE(INDEX(Тест_в2!C16:C19, MATCH("A", C4:F4, 0))), 0) -> 3 | L4: =IFERROR(VALUE(INDEX(Тест_в2!C16:C19, MATCH("B", C4:F4, 0))), 0) -> 1 | M4: =IFERROR(VALUE(INDEX(Тест_в2!C16:C19, MATCH("C", C4:F4, 0))), 0) -> 0 | N4: =IFERROR(VALUE(INDEX(Тест_в2!C16:C19, MATCH("D", C4:F4, 0))), 0) -> 3 | O4: =SUM(K4:N4) -> 7 | R4: Вхохновляющий
B5: 3 | C5: C | D5: A | E5: D | F5: B | H5: С- «Командый» | J5: 3 | K5: =IFERROR(VALUE(INDEX(Тест_в2!C22:C25, MATCH("A", C5:F5, 0))), 0) -> 3 | L5: =IFERROR(VALUE(INDEX(Тест_в2!C22:C25, MATCH("B", C5:F5, 0))), 0) -> 1 | M5: =IFERROR(VALUE(INDEX(Тест_в2!C22:C25, MATCH("C", C5:F5, 0))), 0) -> 0 | N5: =IFERROR(VALUE(INDEX(Тест_в2!C22:C25, MATCH("D", C5:F5, 0))), 0) -> 3 | O5: =SUM(K5:N5) -> 7 | R5: Командный
B6: 4 | C6: B | D6: D | E6: A | F6: C | H6: D- «Процессный» | J6: 4 | K6: =IFERROR(VALUE(INDEX(Тест_в2!C28:C31, MATCH("A", C6:F6, 0))), 0) -> 3 | L6: =IFERROR(VALUE(INDEX(Тест_в2!C28:C31, MATCH("B", C6:F6, 0))), 0) -> 0 | M6: =IFERROR(VALUE(INDEX(Тест_в2!C28:C31, MATCH("C", C6:F6, 0))), 0) -> 1 | N6: =IFERROR(VALUE(INDEX(Тест_в2!C28:C31, MATCH("D", C6:F6, 0))), 0) -> 3 | O6: =SUM(K6:N6) -> 7 | R6: Процессный
B7: 5 | C7: C | D7: B | E7: D | F7: A | J7: 5 | K7: =IFERROR(VALUE(INDEX(Тест_в2!C34:C37, MATCH("A", C7:F7, 0))), 0) -> 3 | L7: =IFERROR(VALUE(INDEX(Тест_в2!C34:C37, MATCH("B", C7:F7, 0))), 0) -> 1 | M7: =IFERROR(VALUE(INDEX(Тест_в2!C34:C37, MATCH("C", C7:F7, 0))), 0) -> 0 | N7: =IFERROR(VALUE(INDEX(Тест_в2!C34:C37, MATCH("D", C7:F7, 0))), 0) -> 3 | O7: =SUM(K7:N7) -> 7 | Q7: Двухвекторный | R7: Целеустремленный и Вдохновляющий
B8: 6 | C8: B | D8: D | E8: A | F8: C | J8: 6 | K8: =IFERROR(VALUE(INDEX(Тест_в2!C40:C43, MATCH("A", C8:F8, 0))), 0) -> 3 | L8: =IFERROR(VALUE(INDEX(Тест_в2!C40:C43, MATCH("B", C8:F8, 0))), 0) -> 0 | M8: =IFERROR(VALUE(INDEX(Тест_в2!C40:C43, MATCH("C", C8:F8, 0))), 0) -> 1 | N8: =IFERROR(VALUE(INDEX(Тест_в2!C40:C43, MATCH("D", C8:F8, 0))), 0) -> 3 | O8: =SUM(K8:N8) -> 7 | R8: Целеустремленный и Командный
B9: 7 | C9: A | D9: C | E9: B | F9: D | J9: 7 | K9: =IFERROR(VALUE(INDEX(Тест_в2!C46:C49, MATCH("A", C9:F9, 0))), 0) -> 3 | L9: =IFERROR(VALUE(INDEX(Тест_в2!C46:C49, MATCH("B", C9:F9, 0))), 0) -> 0 | M9: =IFERROR(VALUE(INDEX(Тест_в2!C46:C49, MATCH("C", C9:F9, 0))), 0) -> 1 | N9: =IFERROR(VALUE(INDEX(Тест_в2!C46:C49, MATCH("D", C9:F9, 0))), 0) -> 3 | O9: =SUM(K9:N9) -> 7 | R9: Целеустремленный и Процессный
B10: 8 | C10: C | D10: B | E10: D | F10: A | J10: 8 | K10: =IFERROR(VALUE(INDEX(Тест_в2!C52:C55, MATCH("A", C10:F10, 0))), 0) -> 3 | L10: =IFERROR(VALUE(INDEX(Тест_в2!C52:C55, MATCH("B", C10:F10, 0))), 0) -> 1 | M10: =IFERROR(VALUE(INDEX(Тест_в2!C52:C55, MATCH("C", C10:F10, 0))), 0) -> 0 | N10: =IFERROR(VALUE(INDEX(Тест_в2!C52:C55, MATCH("D", C10:F10, 0))), 0) -> 3 | O10: =SUM(K10:N10) -> 7 | R10: Вдохновляющий и Командный
B11: 9 | C11: C | D11: B | E11: D | F11: A | J11: 9 | K11: =IFERROR(VALUE(INDEX(Тест_в2!C58:C61, MATCH("A", C11:F11, 0))), 0) -> 3 | L11: =IFERROR(VALUE(INDEX(Тест_в2!C58:C61, MATCH("B", C11:F11, 0))), 0) -> 1 | M11: =IFERROR(VALUE(INDEX(Тест_в2!C58:C61, MATCH("C", C11:F11, 0))), 0) -> 0 | N11: =IFERROR(VALUE(INDEX(Тест_в2!C58:C61, MATCH("D", C11:F11, 0))), 0) -> 3 | O11: =SUM(K11:N11) -> 7 | R11: Вдохновляющий и Процессный
B12: 10 | C12: B | D12: D | E12: A | F12: C | J12: 10 | K12: =IFERROR(VALUE(INDEX(Тест_в2!C64:C67, MATCH("A", C12:F12, 0))), 0) -> 3 | L12: =IFERROR(VALUE(INDEX(Тест_в2!C64:C67, MATCH("B", C12:F12, 0))), 0) -> 0 | M12: =IFERROR(VALUE(INDEX(Тест_в2!C64:C67, MATCH("C", C12:F12, 0))), 0) -> 1 | N12: =IFERROR(VALUE(INDEX(Тест_в2!C64:C67, MATCH("D", C12:F12, 0))), 0) -> 3 | O12: =SUM(K12:N12) -> 7 | R12: Командный и Процессный
B13: 11 | C13: A | D13: C | E13: B | F13: D | J13: 11 | K13: =IFERROR(VALUE(INDEX(Тест_в2!C70:C73, MATCH("A", C13:F13, 0))), 0) -> 3 | L13: =IFERROR(VALUE(INDEX(Тест_в2!C70:C73, MATCH("B", C13:F13, 0))), 0) -> 0 | M13: =IFERROR(VALUE(INDEX(Тест_в2!C70:C73, MATCH("C", C13:F13, 0))), 0) -> 1 | N13: =IFERROR(VALUE(INDEX(Тест_в2!C70:C73, MATCH("D", C13:F13, 0))), 0) -> 3 | O13: =SUM(K13:N13) -> 7 | Q13: Широкий | R13: Целеустремленный, Вдохновляющий, Командный
B14: 12 | C14: C | D14: A | E14: D | F14: B | J14: 12 | K14: =IFERROR(VALUE(INDEX(Тест_в2!C76:C79, MATCH("A", C14:F14, 0))), 0) -> 3 | L14: =IFERROR(VALUE(INDEX(Тест_в2!C76:C79, MATCH("B", C14:F14, 0))), 0) -> 1 | M14: =IFERROR(VALUE(INDEX(Тест_в2!C76:C79, MATCH("C", C14:F14, 0))), 0) -> 0 | N14: =IFERROR(VALUE(INDEX(Тест_в2!C76:C79, MATCH("D", C14:F14, 0))), 0) -> 3 | O14: =SUM(K14:N14) -> 7 | R14: Целеустремленный, Вдохновляющий, Процессный
B15: 13 | C15: D | D15: A | E15: C | F15: B | J15: 13 | K15: =IFERROR(VALUE(INDEX(Тест_в2!C82:C85, MATCH("A", C15:F15, 0))), 0) -> 3 | L15: =IFERROR(VALUE(INDEX(Тест_в2!C82:C85, MATCH("B", C15:F15, 0))), 0) -> 0 | M15: =IFERROR(VALUE(INDEX(Тест_в2!C82:C85, MATCH("C", C15:F15, 0))), 0) -> 1 | N15: =IFERROR(VALUE(INDEX(Тест_в2!C82:C85, MATCH("D", C15:F15, 0))), 0) -> 3 | O15: =SUM(K15:N15) -> 7 | R15: Целеустремленный, Командный, Процессный
B16: 14 | C16: B | D16: D | E16: A | F16: C | J16: 14 | K16: =IFERROR(VALUE(INDEX(Тест_в2!C88:C91, MATCH("A", C16:F16, 0))), 0) -> 3 | L16: =IFERROR(VALUE(INDEX(Тест_в2!C88:C91, MATCH("B", C16:F16, 0))), 0) -> 0 | M16: =IFERROR(VALUE(INDEX(Тест_в2!C88:C91, MATCH("C", C16:F16, 0))), 0) -> 1 | N16: =IFERROR(VALUE(INDEX(Тест_в2!C88:C91, MATCH("D", C16:F16, 0))), 0) -> 3 | O16: =SUM(K16:N16) -> 7 | R16: Вдохновляющий, Командный, Процессный
B17: А- целеустремленный B- вдохновляющий C- командный D- процессный | J17: Сумма баллов по стилю | K17: =SUM(K3:K16) -> 42 | L17: =SUM(L3:L16) -> 7 | M17: =SUM(M3:M16) -> 7 | N17: =SUM(N3:N16) -> 42 | O17: =SUM(K17:N17) -> 98 | Q17: Сбалансированный | R17: Целеустремленный, Вдохновляющий, Командный, Процессный

Sheet Вводная часть отчета
A1: Об отчете
A2: Готово! Мы всё посчитали, ваш результат ниже. Отчёт отображает результаты самодиагностики, полученные при прохождении теста. Ваш отчёт состоит из нескольких блоков: - Введение - Результаты - Характеристика других стилей - Рекомендации по развитию вашего стиля человекоцентричного лидерства
A3: Об инструменте
A4: Инструмент «Тест на определение ведущего стиля человекоцентричного лидерства» помогает понять, как вы создаёте осмысленную, тёплую и результативную рабочую среду для людей в вашей команде. Тест построен на базе: - Модели человекоцентричного лидерства в "Ростелекоме" - Классической двухфакторой модели руководства Ренсиса Лайкерта ("Фокус на людей" и "Фокус на задачи") - Теории контекстов взаимодействия в команде Рэймонда Белбина Человекоцентричное лидерство — это подход к управлению, где в центре решений и внимания лидера всегда находится человек: сотрудник, коллега, клиент, партнёр. Модель человекоцентричного лидерства опирается на четыре вектора: Культура, Лидер, Процессы и практики, Стратегия, и каждому вектору соответствует свой стиль лидерства. Важно: тест не измеряет «уровень» или «индекс» человекоцентричности и не даёт оценочного вердикта. Его задача — помочь лидеру лучше понять особенности своего стиля управления и увидеть, в каких ситуациях этот стиль наиболее эффективен, а где полезно подключать другие подходы.

Sheet Все стили и профили
A1: Тип профиля | B1: Ведущие стили | C1: Характеристика | D1: Как мне повысить человекоцентричность в моей команде? (рекомендации по развитию)
A2: Сфокусированный | B2: Целеустременный | C2: Стиль ориентирован на результат и создание ценности для клиентов. В модели человекоцентричности ему соответствует вектор «Стратегия». Приоритеты лидера — цели, достижения, своевременные решения, ценность для клиента и общества, Целеустремлённый лидер проявляет человекоцентричность через ясность целей, фокуса в работе и достижение результата, который приносит пользу клиенту и компании. Такой лидер фокусируется на показателях, контроле выполнения задач и достижении оговорённого результата. Сильные стороны - Ориентация на ценность для клиента и общества; - Быстрые и качественные решения в условиях неопределённости; - Умение удерживать фокус и выделять приоритеты; - Ясность целей и измеримый результат. Как стиль влияет на человекоцентричную культуру в Ростелекоме? Ваш ведущий стиль формирует культуру ответственности за результат и осмысленной работы «не ради цифры, а ради пользы». Лидер показывает связь задач команды с ценностью для клиента и бизнеса, даёт ясные ориентиры, понятные показатели, чёткие планы и синхронизирует работу команды с тем, какую пользу она приносит компании и клиентам. Ваш стиль человекоцентричности эффективен в ситуациях, если: - Нужно быстро принять решение и сфокусировать команду на приоритетах в условиях неопределённости; - Команде важно понять, как её работа создаёт ценность для клиента и бизнеса, в том числе в долгосрочной перспективе; - В команде много задач и проектов и нужна ясность целей, сроков и измеримого результата; - Возник риск нарушения сроков и нужно оперативно перераспределить нагрузку, сохраняя качество решений. Ваш стиль человекоцентричности менее эффективен, если: - Важно сфокусироваться на построении отношений и взаимопонимания внутри команды; - Требуется пересмотреть и упростить бизнес-процессы; - Команде нужно выделить время и ресурс на индивидуальные траектории развития компетенций. | D2: Попробуйте расширить набор инструментов лидера: оставить фокус на создании ценности для клиента и бизнеса, но укрепить команду через понимание людей, их мотивации, раскрытия потенциала, усиление эффективности процессов. Для этого: Узнайте больше о своей команде: - Проведите индивидуальные беседы: понимает ли каждый сотрудник, как его работа влияет на клиента и компанию, или видит только свои КПЭ/MBO. - Спросите, где темп решений и многозадачность помогают, а где создают перегруз и снижают качество. - Соберите обратную связь: достаточно ли в команде уважительного общения и взаимопомощи, а также условий для роста. - Проанализируйте, где "размытость" ролей и лишние барьеры мешают людям достигать результата. Внедряйте в практику и делайте чаще: - На командных встречах совмещайте приоритеты и решения с тем, как команда помогает друг другу; - Давайте сотрудникам задачи на развитие и обратную связь о зонах роста; - Упрощайте согласования и убирайте лишние шаги на пути к результату; - Выделяйте личный вклад сотрудников в ценность для клиента; - Помогайте строить индивидуальные траектории развития, помогайте расти. Закрепите изменения и дополните свой стиль: - Развивайте культуру уважительной обратной связи. - Обсудите вместе с сотрудниками их индивидуальные траектории развития компетенций: в чём их сильные стороны, а какие навыки можно усилить. - Регулярно пересматривайте «узкие места» процессов, которые мешают людям работать эффективно.
A3: Сфокусированный | B3: Вхохновляющий | C3: Стиль ориентирован на развитие людей. Вектор в модели человекоцентричности — Лидер. Приоритеты — раскрытие потенциала, создание условий для роста, возможности для профессионального и личностного развития. Вдохновляющий лидер проявляет человекоцентричность через развитие и мотивацию других: он видит потенциал сотрудников, создаёт условия для обучения и роста, даёт амбициозные задачи и поддерживает траекторию развития. Сильные стороны: - Создание условий для раскрытия потенциала сотрудников; - Возможности для роста и обучения; - Мотивация через личный пример развития; - Формирование амбициозного видения «кем мы можем стать». Как стиль влияет на человекоцентричную культуру в Ростелекоме? Ваш ведущий стиль укрепляет культуру непрерывного развития и веры в потенциал людей. Лидер показывает, что Ростелеком инвестирует в человека: даёт задачи для роста, обратную связь, наставничество. Вдохновляющий стиль наполняет работу команды пониманием своих возможностей для профессионального и карьерного роста. Ваш стиль человекоцентричности эффективен, если: - Сотрудникам нужны задачи для роста, обратная связь и условия для раскрытия потенциала; - Важен личный пример лидера и амбициозное видение; - Формируется новая команда и нужно заложить культуру наставничества и развития; - Необходимо создать пространство для обучения, освоения новых компетенций для профессионального/карьерного роста. Ваш стиль человекоцентричности менее эффективен, если: - Стоят жёсткие сроки и есть необходимость чёткого операционного контроля; - Нужны прозрачные договорённости, роли и предсказуемость бизнес-процессов; - Нужны системные правила и фокус на оптимизацию процессов. - Нужно сосредоточиться на построении доверительной атмосферы и взаимопонимания между сотрудниками; | D3: Попробуйте расширить набор инструментов лидера: сохранить фокус на драйве и энергии руководителя, его стремлении развивать команду, но усилить управляемость через цели, контрольные точки и ясные бизнес-механизмы, а также фокус на создании команды как единого целого для более долгосрочной работы. Для этого: Узнайте больше о своей команде: - Узнают, все ли рабочие процессы выстроены оптимально или где-то требуется их перестройка; - Уточните, видят ли сотрудники связь между их ростом и ценностью для клиента и бизнеса; - Проверьте, есть ли понятные договорённости о целях, сроках и критериях успеха; - Спросите, достаточно ли текущего уровня общения в команде — норма, которую вы поддерживаете. Комфортно ли сотрудникам работать в команде? Внедряйте в практику и делайте чаще: - Связывайте задачи на рост с реальной пользой для клиента и общества; - Фиксируйте контрольные точки и критерии успеха по проектам; - Развивайте к команде доброжелательную среду, усиливайте сплоченность; - Регулярно проводите встречи с целью обсуждения эффективности работы текущих процессов и вовремя их оптимизируйте. Закрепите изменения и дополните свой стиль: - Ставьте четкие цели с измеримым результатом. - Раз в квартал обсуждайте: как наш рост влияет на клиента и компанию. - Упростите правила взаимодействия там, где неясность мешает людям расти. - Поддерживайте уважительный и доброжелательный тон общения в команде. - Создавайте простые удобные и эффективные рабочие процессы.
A4: Сфокусированный | B4: Командный | C4: Стиль ориентирован на команду и культуру взаимодействия. Вектор в модели человекоцентричности — Культура. Приоритеты — доброжелательное общение, уважительная коммуникация, культура взаимопомощи, ролевая модель корпоративной культуры. Командный лидер проявляет человекоцентричность через то, как команда общается и поддерживает друг друга: он демонстрирует уважительный диалог, тактичность и вежливость в общении, готовность помочь и быть опорой. Он — ролевая модель корпоративной культуры: показывает на своём примере, как принято общаться, договариваться и взаимодействовать в компании. Сильные стороны: - Доброжелательная культура общения; - Уважительная коммуникация и конструктивная обратная связь; - Культура взаимопомощи и создание психологической безопасности; - Ролевая модель корпоративных ценностей в ежедневном поведении. Как стиль влияет на человекоцентричную культуру в Ростелекоме? Ваш ведущий стиль задаёт «тон общения» в команде и вокруг неё: люди чувствуют, что их слышат, к ним относятся с уважением, можно просить помощи. Лидер укрепляет человекоцентричность через живое воплощение культуры Ростелекома — не через декларирование, а ежедневные взаимодействия. Ваш стиль человекоцентричности эффективен в ситуациях, если: - Команде важен уважительный диалог, тактичность и взаимопомощь; - Людям нужен медиатор или фасилитатор для достижения договорённостей; - Необходимо адаптировать новых сотрудников, обеспечить комфортную среду, поддержку и «опору». Ваш стиль человекоцентричности менее эффективен, если: - Нужно быстро принять непопулярное решение; - Требуется достижение амбициозных результатов в короткие сроки, - Нужно снять барьеры в процессах, оптимизировать их. - Команде важен профессиональный вызов или внедрение инноваций. | D4: Попробуйте расширить набор инструментов лидера: сохранить фокус на команде и взаимоотношениях, но усилить управляемость через ясные роли, измеримые договоренности и контроль прогресса. Для этого: Узнайте больше о своей команде: - Спросите, понимает ли команда, какую ценность для клиента и компании создаёт их работа - Проверьте, зафиксированы ли договорённости о ролях, сроках и ответственности - Уточните, прозрачны и ясны ли для команды цели и процессы Внедряйте в практику и делайте чаще: - Продолжайте совершенствовать командные правила взаимодействия, например, о том, как даём обратную связь, как спорим, как просим помощи. - На встречах больше обсуждайте, «какую ценность для клиента мы создаём». - Фиксируйте решения письменно: кто, что, к какому сроку выполняет. - В сложных ситуациях практикуйте не только уважительный, но и прямой разговор. - Обозначайте личную ответственность сотрудников Скорректируйте/ Закрепите изменения и дополните свой стиль: - Четко формулируйте цели и контролируйте достижение результата. - Всегда сверяйтесь: создают ли ваши решения ценность для клиента и компании. - Упростите лишние согласования. - Введите в свою практику содействие сотрудникам в выборе вектора развития и формировании карьерной траектории.
A5: Сфокусированный | B5: Процессный | C5: Стиль ориентирован на организацию работы. Вектор в модели человекоцентричности — Процессы и практики. Приоритеты — прозрачность, понятные договорённости, устранение барьеров, предсказуемость. Процессный лидер проявляет человекоцентричность через удобную и понятную среду работы: он выстраивает правила взаимодействия, убирает лишние препятствия и создаёт условия, в которых сотрудник может сосредоточиться на задаче. Основная цель — обеспечить максимальную эффективность через отлаженный и структурированный подход, делая акцент на том, чтобы процессы помогали людям, а не мешали им. Сильные стороны: - Прозрачность и предсказуемость в работе; - Устранение организационных барьеров; - Оптимизация взаимодействий между людьми и подразделениями; - Снижение неопределённости «как договориться и что делать». Как стиль влияет на человекоцентричную культуру в Ростелекоме: Ваш ведущий стиль формирует культуру уважения к времени и усилиям людей: меньше хаоса, больше ясности. Лидер показывает, что человекоцентричность — это не бюрократия, а продуманная и организованная среда, где каждый понимает свою роль и может эффективно работать. Ваш стиль человекоцентричности эффективен в ситуациях, если: - Команде нужны прозрачность и предсказуемость работы; - Масштабируется типовая работа и важен понятный, воспроизводимый способ действий; - Необходимо упрощение процессов и чёткость ролей и зон ответственности. Ваш стиль человекоцентричности менее эффективен в ситуациях, если: - Требуется фокус на инновации и эксперименты; - Нужно сосредоточиться на построении доверительной атмосферы и взаимопонимания между сотрудниками; - Команде не хватает мотивации и индивидуального подхода к развитию. - Нужны более четкие цели, достижение результата в сжатые сроки. | D5: Попробуйте расширить набор инструментов лидера: сохранить фокус на процессах и эффективности, но усилить управляемость через создание доброжелательной и уважительной среды в команде, мотивацию, делегирование и развитие людей. Для этого: Узнайте больше о своей команде: - Соберите обратную связь, где процессы реально помогают, а где создают «трение»; - Выясните, видит ли команда связь своей работы с ценностью для клиента и компании; - Оцените, достаточно ли уважительного общения и взаимопомощи; - Узнайте, известны ли сотрудникам их возможности для роста, раскрывают ли они свой потенциал. Внедряйте в практику и делайте чаще: - При описании задач добавляйте, зачем это клиенту и бизнесу; - Уделяйте больше времени созданию сплоченной команды; - Поддерживайте уважительное общение в команде; - Давайте сотрудникам задачи на развитие, помогайте им усиливать свои компетенции; - В нестандартных ситуациях делайте пилоты и проводите эксперименты для проверки своих гипотез. Скорректируйте/ Закрепите изменения и дополните свой стиль: - Развивайте культуру, в которой сотрудник не боится допускать ошибку; - Фиксируйте образ результата и критерии достижения успеха; - Развивате навыки действий в условиях неопределенности; - Связывайте изменения процессов с ценностью для клиента; - Развивайте взаимопомощь и поддержку в команде; - Поддерживайте индивидуальное развитие компетенций.
A6: Двухвекторный профиль | B6: Целеустремленный и Вдохновляющий | C6: Сочетание данных стилей объединяет ориентацию на результат, создание ценность для клиента и Общества (целеустремленный стиль), а также фокус развитие потенциала и мотивацию сотрудников (вдохновляющий стиль). Векторы в модели человекоцентричности: «Стратегия» и «Лидер». Приоритеты лидера — достижение амбициозных целей через вдохновение и развитие сотрудников . Такой лидер ставит команде высокие цели, которые направлены на создание пользы для Общества и клиентов, мотивирует и развивает для их достижения. Сильные стороны - Создание амбициозного видения, связанного с измеримыми результатами; - Мотивация сотрудников с опорой на то, какую ценность результаты принесут клиентам; - Принятие быстрых решений без потери фокуса на рост и раскрытие потенциала подчиненных; - Развитие сотрудников через амбициозные задачи; - Формирование культуры результативности, в которой каждый может развивать свою карьеру. Как стиль влияет на человекоцентричную культуру в Ростелекоме? Стиль формирует культуру амбициозного развития с ясным результатом. Лидер показывает, что в команде понятные цели, они измеримы и связаны с пользой для клиента. В таком подходе сотрудники чувствуют, что их потенциал видят и дают задачи «на вырост»; а высокая требовательность к результату сочетается с верой в возможности команды. Ваш стиль человекоцентричности эффективен, если: - Компании нужно одновременно достичь амбициозных целей и вырастить новых лидеров-преемников; - Команда снизила позитивный настрой и мотивацию; - Стоит задача трансформации или запуска нового направления, где важны и скорость, и вовлечение людей; - Сотрудники обладают высоким потенциалом, но им не хватает ясности целей и связи с результатом — вы сочетаете и то, и другое; - Нужно увлечь команду долгосрочной стратегией, не теряя фокуса на текущих KPI. Ваш стиль человекоцентричности менее эффективен, если: - В текущих приоритетах работы — операционный контроль и создание регламентации. - Нужно построить или восстановить доверие и уважительные\доброжелательные коммуникации в команде после конфликта. - Требуется фокус на упрощение текущих процессов. - Команде нужна не вдохновляющая цель, а чёткие, стабильные правила и предсказуемость. | D6: Попробуйте расширить набор инструментов лидера: сохранить сочетание амбициозных целей и развитие потенциала людей, но усилить управляемость через фокус на укрепление командных отношений и создание прозрачных рабочих процессов. Узнайте больше о своей команде: - Проведите индивидуальные беседы и узнайте: достаточно ли в команде взаимопомощи, чувствуют ли сотрудники, что могут обратиться за поддержкой, не боясь давления. - Узнайте, насколько сотрудники чувствуют себя частью команды, а не отдельно взятыми игроками, нет ли в команде скрытых конфликтов и напряжения. - Проанализируйте, достаточно ли чётко распределены роли, зоны ответственности, а регламенты понятны и актуальны. - Спросите: какие процессы и согласования отнимают больше всего времени и создают барьеры. Внедряйте в практику и делайте чаще: - Регулярно проводите командные встречи, где можно обсудить не только результаты, но и то, как сы работаем вместе: что помогает, а что мешает сотрудничеству. - В конце встреч выделяйте немного времени, чтобы каждый мог поблагодарить коллегу за помощь, поддержку или хорошую идею. - Периодически задавайте вопросы, которые помогут вам узнать состояние команды и своевременно понять, где внимания нужно больше. - Вместе с командой составьте карту «узких мест»: где согласования занимают слишком много времени, где роли размыты, где информация теряется. - Убедитесь, что каждый понимает, за что отвечает лично он, а за что — коллеги. Это повысит организованность и порядок. - Введите «процессные ретроспективы»: периодически разбирайте не только что сделано (результат), но и как - какие процессы помогали, какие мешали, что можно улучшить. Закрепите изменения и дополните свой стиль: - Перед запуском новой амбициозной задачи задайте себе вопросы: учтена ли потребность команды в теплых доверительных отношениях; какие процессы я буду улучшать, чтобы в будущем выполнение подобной задачи стало более системным и предсказуемым. - Назначьте «хранителя процессов» в команде. Если у вас нет склонности к деталям, делегируйте контроль за регламентами сотруднику, который в этом силён. - Развивайте культуру взаимопомощи через ценность для клиента. Свяжите командное взаимодействие с результатом: «Когда мы помогаем друг другу, клиент получает лучший сервис быстрее». | U6: 19
A7: Двухвекторный профиль | B7: Целеустремленный и Командный | C7: Сочетание данных стилей объединяет ориентацию на результат, создание ценности для клиента и Общества (целеустремленный стиль) и команду, культуру взаимодействия и уважительных коммуникаций (командный стиль). Векторы в модели человекоцентричности: «Стратегия» и «Культура». Приоритеты лидера — достижение измеримых целей через уважительное общение, доверие и командную работу. Такой лидер создаёт среду, где люди чувствуют поддержку и могут эффективно договариваться и при этом сфокусированы на достижение высоких результатов. Сильные стороны: - Достижение амбициозных целей в атмосфере доверия; - Требования и уважение: лидер стремится к достижению результатов, но не упускает создание уважительных и тактичных отношений в команде; - Принятие быстрых решений; - Создание сплоченной команды. Как стиль влияет на человекоцентричную культуру в Ростелекоме? Стиль формирует культуру ориентации на результат, достижение измеримых целей в доброжелательной командой среде. Лидер показывает, что достигать высокие цели можно в атмофере доверия, взаимопомощи и уважения. Ваш стиль человекоцентричности эффективен, если: - Нужно достичь амбициозных целей, укрепив при этом укрепив командный дух; - В команде есть напряжение или недопонимание- вы поможете разрешить сложную ситуацию; - Команда состоит из разных сильных экспертов, и нужен баланс между результатом и взаимоотношениями; - Компания переживает изменения, и важно одновременно сохранить фокус на результате и поддержать людей. Ваш стиль человекоцентричности менее эффективен, если: - Команде нужно выделить время и ресурс на индивидуальные траектории развития; - Требуется фокус на создание прозрачных рабочих процессов и регламентов; - Нужно предоставить сотруднику больше свободы для самостоятельного поиска решений. | D7: Попробуйте расширить набор инструментов лидера: сохранить сочетание амбициозных целей и укрепление командных отношений, но усилить управляемость через развитие потенциала сотрудников и оптимизацию рабочий процессов. Узнайте больше о своей команде: -Узнайте, видят ли сотрудники связь между своей текущей работой и возможностью профессионального и карьерного роста. -Обсудите с сотрудниками, есть ли уних индивидуальные траектории развития, помогите в их составлении -Проанализируйте, насколько прозначны и эффективны текущие бизнес-процессы -Уточните, есть ли узкие места, где постоянно возникают сбои из-за отсутствия стандартных процедур -Проясните, достаточно ли в команде системных правил, которые работают без вашего участия Внедряйте в практику и делайте чаще: -В начале работы с новой задачей формулируйте связь с развитием-какие новые навыки могут появиться -Проводите регулярные индивидуальные встречи, направленные на развитие, делитесь личным примером -Отмечайте личный рост сотрудников, их инициативы -Письменно фиксируйте ключевые договоренности -Введите регулярные ретроспективы по разбору процессов Закрепите изменения и дополните свой стиль: -Перед запуском новой задачи задавайте себе вопросы: какие навыки я помогу развивать сотрудникам в этой задаче? Какие процессы я буду улучшать, чтобы в будущем выполнение подобной задачи стало более системным и предсказуемым. - Назначьте «хранителя процессов» в команде. Если у вас нет склонности к деталям, делегируйте контроль за регламентами сотруднику, который в этом силён. - Развивайте культуру обратной связи о возможностях развития в команде, транслируйте вновь появляющиеся ресурсы для роста и развития карьеры в Комании.
A8: Двухвекторный профиль | B8: Целеустремленный и Процессный | C8: Сочетание данных стилей объединяет фокус на достижение результатов, создание ценности для клиентов и Общества (целеустремленный стиль), а также организацию работы, прозрачность в процессах (процессный стиль). Векторы в модели человекоцентричности- Стратегия и Процессы и практики. Приоритеты лидера — достижение амбициозных, измеримых целей через отлаженные, прозрачные и эффективные процессы. Лидер создаёт среду, в которой каждый понимает свою роль, зону ответственности и то, как его работа ведёт к результату. Сильные стороны: -Ясные цели и прозрачные процессы- сотрудники понимают образ результата и четкий пусть его достижения; -Быстрые решения, подкрепленные зафиксированными правилами; -Создание отлаженных, четких рабочих процессов; -Предсказуемость и надежность- команда знает, что в какие сроки и каким образом необходимо выполнить; -Организованный рабочий процесс, который направлен на создание ценности для клиентов и Общества. Как стиль влияет на человекоцентричную культуру в Ростелекоме: Стиль формирует культуру результативности и порядка. Лидер показывает, как отлаженная система работы помогает сотрудникам сосредоточиться на достижении результатов, двигаться к целям без неопределенности в процессах. Ваш стиль человекоцентричности эффективен в ситуациях, если: - Команде нужна прозрачность: понятные роли, сроки, критерии успеха; - Масштабируется типовая работа и требуется воспроизводимый, эффективный способ действий; - Нужно быстро принять решение и сфокусировать команду на приоритетах в условиях неопределённости; - Команде важно понять, как её работа создаёт ценность для клиента и бизнеса, в том числе в долгосрочной перспективе; Ваш стиль человекоцентричности менее эффективен в ситуациях, если: - Важно сфокусироваться на построении отношений и взаимопонимания внутри команды; - Команде нужно выделить время и ресурс на индивидуальные траектории развития компетенций. - Команда пережила конфликт или потеряла доверие — первичны восстановление отношений и психологическая безопасность; - Сотрудник осваивает новую роль и нужна поддержка, а не только ускорение; | D8: Попробуйте расширить набор инструментов лидера: сохранить фокус результатах, создании ценности для клиентов и Общества, а также на процессах и эффективности, но усилить управляемость через создание доброжелательной и уважительной среды в команде, мотивацию и развитие людей. Для этого: Узнайте больше о своей команде: -Соберите обратную связь, достаточно ли в команде уважительного общения, взаимопомощи и доверия; -Узнайте, известны ли сотрудникам их возможности для роста, раскрывают ли они свой потенциал; -Проясните, чувствуют ли себя сотрудники частью команды; - Обсудите с сотрудниками, видят ли они связь между текущими задачами и возможностями для развития новых навыков. Внедряйте в практику и делайте чаще: - Создавайте пространство для открытого диалога; - В конце встреч выделяйте немного времени, чтобы каждый мог поблагодарить коллегу за помощь; - Чаще обсуждайте состояние и атмосферу в команде; - Развивайте культуру уважительной обратной связи; - В сложных ситуациях практикуйте не только четкие, но и эмпатичные разговоры; - Регулярно проводите индивидуальные встречи, посвященные развитию сотрудников; - Делитесь личным примером развития. Скорректируйте/ Закрепите изменения и дополните свой стиль: - Развивайте культуру, в которой сотрудник не боится допускать ошибку; - Развивайте взаимопомощь и поддержку в команде, уделяйте больше внимания вопросам сплоченности; - Поддерживайте индивидуальное развитие компетенций.
A9: Двухвекторный профиль | B9: Вдохновляющий и Командный | C9: Сочетание данных стилей объединяет фокус на культуру взаимодействия, создание доброжелательной атмосферы в команде (командный стиль), а также развитие и мотивацию сотрудников (вдохновляющий стиль). Векторы в модели человекоцентричности- Культура и Лидер. Приоритеты- создание доверительной, уважительной атмосферы, в которой каждый человек чувствует поддержку, поддержка индивидуального роста и развития сотрудников. Сильные стороны: - Создание условий для раскрытия потенциала сотрудников; - Возможности для роста и обучения; - Доброжелательная культура общения; - Уважительная коммуникация и конструктивная обратная связь; - Культура взаимопомощи и создание психологической безопасности; Как стиль влияет на человекоцентричную культуру в Ростелекоме? Ваш стиль формирует культуру развития в сочетании с уважениее и поддержкой в команде. Лидер показывает, что человекоцентричность — это тёплая доброжелательная атмосфера в команде и активное участие в развитии людей: обучении, новых вызовах, верой в потенциал и мотивации. Ваш стиль человекоцентричности эффективен, если: - Нужно адаптировать новых сотрудников и обеспечить их быстрый рост и комфортное вхождение в культуру; - Команде не хватает мотивации и веры в свои возможности - Формируется новая команда и нужно заложить культуру наставничества, уважения и непрерывного развития; - Требуется развить сотрудников до новых ролей, сохранив при этом лояльность и вовлечённость. Ваш стиль человекоцентричности менее эффективен, если: - К текущих рабочих приоритетах — жёсткие сроки и операционный контроль; - Требуются прозрачные договорённости, предсказуемость и отлаженность рабочих процессов. - Нужно быстро принять непопулярное кадровое решение - Важнее сфокусироваться на четкой структуре и ясных критериях успеха. | D9: Попробуйте расширить набор инструментов лидера: сохранить фокус на команде и взаимоотношениях, а также развитии и мотивации, но усилить управляемость через измеримые цели, фокус на создании ценности для клиентов и Общества, а также оптимизацию рабочих процессов Для этого: Узнайте больше о своей команде: - Видят ли сотрудники связь между своими задачами и бизнес-результатами для клиентов и Общества; - Спросите, насколько команде ясны общие цели и измеримые критерии успеха; - Проверьте, насколько быстро команда способна принимать решения в условиях неопределённости; - Проанализируйте прозрачность и эффективность рабочих процессов; - Проясните четкость ролей и зон ответственности у каждого сотрудника. Внедряйте в практику и делайте чаще: - При поставновке задачи не упускайте формулирование измеримого результата, какую ценность для клиента и Общества принесет результат; - Фиксируйте цели и KPI по проектам, а также ключевые договоренности письменно; - Вы можете оставаться тактичным и доброжелательным, но при этом чётко обозначать ожидания по срокам и качеству; - Определите роли и зоны ответственности сотрудников в ключевых процессах; - Составьте с командой карту "узких" мест- что препятствуют достижению качественных результатов, оптимизируйте эти процессы. Скорректируйте/ Закрепите изменения и дополните свой стиль: -Перед запуском новой задачи отвечайте себе на вопросы: Как я обеспечу измеримый результат и ценность для клиента в этой задаче? Какие процессы, промежуточные точки контроля я зафиксирую? - Закрепите норму: «Все задачи мы доводим до результата»; - Сверяйтесь: создают ли ваши решения ценность для клиента и компании; - Упростите или измените процессы, которые уже устарели и перестали быть эффективными.
A10: Двухвекторный профиль | B10: Вдохновляющий и Процессный | C10: Сочетание данных стилей объединяет фокус на развитие людей, раскрытие их потенциала, мотивацию (вдохновляющий стиль) и организацию работы, создание прозрачности в рабочих процессах (процессный стиль). В модели человекоцентричности- это два вектора: «Лидер» и «Процессы и практики». Приоритеты лидера — создание условий, в которых люди могут расти и развиваться, опираясь на понятные, четкие и эффективные процессы. Руководитель строит систему, в которой развитие становится предсказуемым и встроенным в повседневную работу. Сильные стороны: -Создание системы индивидуального развития сотрудников; -Мотивация и вдохновение команды на новые задачи; - Рост и продвижение сотрудников; - Формирование отлаженных рабочих-процессов; - Прозрачность и предсказуемость в работе. Как стиль влияет на человекоцентричную культуру в Ростелекоме: Ваш стиль формирует культуру развития и порядка. Лидер показывает, что человекоцентричность - это создание понятной, удобной среды, траекторий развития, в которых каждый может реализовать свой потенциал. Ваш стиль человекоцентричности эффективен в ситуациях, если: - Нужно выстроить системное обучение и развитие в команде; - Команде нужна прозрачность и предсказуемость, в том числе в карьерных треках и возможностях роста; - Масштабируется практика наставничества и развития; - Необходимо выстраивать системные бизнес-процессы; - Нужно четко выделить зоны ответстенности и роли в команде. Ваш стиль человекоцентричности менее эффективен в ситуациях, если: - Нужно сосредоточиться на построении доверительной атмосферы и взаимопонимания между сотрудниками; - Нужно действовать в условиях сжатых сроков и неопределенности; - Команде требуется неформальная поддержка и восстановление отношений после конфликта | D10: Попробуйте расширить набор инструментов лидера: сохранить фокус на процессах и индивидуальном развитии и мотивации сотрудников, но усилить управляемость через создание доброжелательной среды в команде, ориентации на результат и создании ценности для клиентов и Общества. Узнайте больше о своей команде: - Узнайте, понимает ли каждый сотрудник связь между своим развитием, процессами и реальной ценностью для клиента и бизнеса; - Спросите, достаточно ли в команде ясности целей, приоритетов и измеримых результатов; - Проясните, насколько быстро команда способна принимать решения в условиях жёстких сроков; - Узнайте, достаточно ли в команде уважительного общения и взаимопомощи; - Уточните, насколько сотрудники чувствуют себя частью сплочённой команды, объединенной общей целью; - Узнайте, достаточно ли в команде неформального общения и эмпатии. Внедряйте в практику и делайте чаще: - На командных встречах и ретроспективах процессов уделяйте время обсуждению измеримых результатов и ценности для клиента - Развивайте навыки принятия быстрых решений в условиях неопределенности; - Создавайте пространство для открытого, неформального диалога; - В конце встреч уделяйте немного времени, чтобы каждый мог поблагодарить коллегу за помощь, поддержку; - Обсуждайте не только процессы и индивидуальное развитие, но и состояние команды как единого целого; Скорректируйте/ Закрепите изменения и дополните свой стиль: - Связывайте изменения процессов с ценностью для клиента; - Проясняйте образ результата и критерии успешности выполнения задач; - Развивайте взаимопомощь и поддержку в команде; - Поддерживайте эмпатичные доброжелательные коммуникации.
A11: Двухвекторный профиль | B11: Командный и Процессный | C11: Сочетание данных стилей объединяет ориентацию на команду, культуру взаимодействия и создание доброжелательных отношений (командный стиль) , а также организацию работы, прозрачность в рабочих процессах (процессный стиль). Векторы в модели человекоцентричности: «Культура» и «Процессы и практики». Приоритеты лидера — создание доброжелательной, уважительной среды и параллелельно — прозрачных, понятных и эффективных процессов. Сильные стороны: -Создание порядка и доброжелательной командной атмосферы; -Лидер заботится о людях и их эффективности, создавая четко отлаженные процессы; -Создание четких договоренностей в уважительном тоне; -Надёжная среда для адаптации: новые сотрудники получают и поддержку, и понимание процессов, ролей и ответственности; Как стиль влияет на человекоцентричную культуру в Ростелекоме: Ваш стиль формирует культуру порядка, основанного на уважении. Лидер показывает, что человекоцентричность - это гармоничное сочетание: когда процессы продуманы и прозрачны, людям комфортнее работать, а когда в команде уважение и поддержка — процессы внедряются легче и с меньшим сопротивлением. Ваш стиль человекоцентричности эффективен в ситуациях, если: - Команде нужны одновременно прозрачность, предсказуемость и уважительная, поддерживающая атмосфера; - Необходимо наладить уважительные коммуникации; - Нужно создать сплоченную рабочую среду; - Масштабируется типовая работа; - Нужно упростить и оптимизировать процессы; Ваш стиль человекоцентричности менее эффективен в ситуациях, если: - Требуется фокус на инновации и эксперименты; - Команде не хватает мотивации и индивидуального подхода к развитию. - Команда находится в условиях жестких сроков и неопределенности - Команде требуются амбициозные, развивающие их новые навыки, задачи | D11: Попробуйте расширить набор инструментов лидера: сохранить фокус на процессах и эффективности, а также создании доброжелательных уважительных коммуникаций в команде но усилить управляемость через создание амбициозные цели, приносящие ценность клиенту и Обществу и мотивацию, делегирование и развитие людей. Для этого: Узнайте больше о своей команде: - Спросите, достаточно ли в команде ясности целей, приоритетов и измеримых результатов; - Выясните, видит ли команда связь своей работы с ценностью для клиента и компании; - Проясните, насколько быстро команда способна принимать решения в условиях неопределённости и срочности; - Узнайте, известны ли сотрудникам их возможности для роста, раскрывают ли они свой потенциал. - Поговорите с сотрудниками, достаточно ли амбициозных задач, которые бросают вызов и вдохновляют. Внедряйте в практику и делайте чаще: - При описании задач добавляйте, зачем это клиенту и бизнесу; - При работе с задачей формулируйте образ измеримого результата; - Продолжайте развивать навык постановки целей по Smart - Проводите регулярные встречи, посвященные развитию; - Давайте сотрудникам больше задач на развитие за пределами привычных им рабочих процессов. Скорректируйте/ Закрепите изменения и дополните свой стиль: - Развивайте компетенции принятия быстрых решений в том числе в условиях неопределенности; - Связывайте изменения процессов с ценностью для клиента; - Поддерживайте индивидуальное развитие компетенций; - Развивайте культуру, в которой сотрудник не боится допускать ошибку.
A12: Широкий профиль | B12: Целеустремленный, Вдохновляющий, Командный | C12: Сочетение данных стилей объединяет фокус на достижение результата, создание ценности для клиента и Общества (целеустремленный стиль); мотивацию, развитие людей и раскрытие их потенциала (вдохновляющий стиль); а также создание доброжелательной и уважительной командной атмосферы (командный стиль). Приоритет лидера -достижение высоких целей через вдохновение, развитие людей и уважительную командную культуру. Векторы в модели человекоцентричности- Стратегия, Лидер и Команда. Сильные стороны: - Достижение амбициозных целей, вдохновение и поддержка сотрудников; - Быстрые решения с учётом возможностей и потенциала команды; - Ориентация на создание ценности для клиента и общества; - Доброжелательная культура общения; - Уважительная коммуникация и конструктивная обратная связь; - Создание условий для раскрытия потенциала сотрудников; - Возможности для роста и обучения. Как стиль влияет на человекоцентричную культуру в Ростелекоме? Ваш стиль формирует культуру достижения высоких целей с опорой на команду и вклад в индивидуальное развитие сотрудников. Лидер показывает, как можно достигать измеримый с помощью мотивации и вклада в развитие индивидуальных компетенций сотрудников, а также через создание сплоченной командной работы. Ваш стиль человекоцентричности эффективен в ситуациях, если: - Нужно быстро достичь амбициозных результатов, вдохновляя и объединяя команду; - Стоит задача трансформации или запуска нового направления, где важны и скорость, и вовлечение, и развитие людей; - В команде есть напряжение между «достигаторами» и «хранителями культуры» — вы можете их объединить. Ваш стиль человекоцентричности менее эффективен, если: - в текущих приоритетах налаживание операционных процессов; - нужна системная, повторяемая работа с минимальными отклонениями; - команде нужна стабильная работа с понятными правилами | D12: Попробуйте расширить набор инструментов лидера: сохранить фокус на команде и взаимоотношениях, измеримых целях и развитии сотрудников, но усилить управляемость через ясные роли, прозрачные договоренности и оптимизацию рабочих процессов. Для этого: Узнайте больше о своей команде: - Проверьте, зафиксированы ли договорённости о ролях и ответственности; - Проанализируйте, насколько прозрачны и эффективны текущие бизнес-процессы; - Спросите, достаточно ли в команде системных правил, которые работали бы во время вашего отсутствия; Внедряйте в практику и делайте чаще: - Фиксируйте ключевые договорённости письменно; - Определите роли и зоны ответственности в процессах; - Составьте карту "узких" мест и оптимизируйте их; - Внедрите регулярные «ретроспективы процессов» Скорректируйте/ Закрепите изменения и дополните свой стиль: - Упростите правила взаимодействия чёткими договорённостями зон ответственности, ролей, сроков выполнения задач. - Если вы не склонны к поддержанию процессов и работе по четким правилам, развивайте эту роль у сотрудников, делегируйте; - Периодически обсуждайте с командой: как наши процессы помогают или мешают достигать целей, развиваться и поддерживать друг друга.
A13: Широкий профиль | B13: Целеустремленный, Вдохновляющий, Процессный | C13: Сочетание данных стилей объединяет фокус на достижение результатов, создание ценности для клиентов и Общества (целеустремленный стиль); на организацию работы, прозрачные бизнес-процессы (процессный стиль); и мотивацию и развитие сотрудников (вдохновляющий стиль). Векторы в модели человекоцентричности — Стратегия, Лидер, Процессы и практики. Приоритеты - достижение амбициозных целей через развитие людей и выстроенные, эффективные процессы. Сильные стороны: - Прозрачность и предсказуемость в работе; - Четкая организация работы команды; - Ориентация на ценность для клиента и общества; - Быстрые и качественные решения в условиях неопределённости; - Создание условий для раскрытия потенциала сотрудников; - Возможности для роста и обучения; Как стиль влияет на человекоцентричную культуру в Ростелекоме: Ваш стиль формирует культуру, в которой каждый понимает цели и видит, как их достижение приносит ценность для клиента и Общества и помогает развивать профессиональные компетенции, а также выстраивает эффективные рабочие процессы. Ваш стиль человекоцентричности эффективен в ситуациях, если: - Нужно достичь амбициозных целей, одновременно развивая команду и выстраивая эффективные процессы; - Команде нужны одновременно ясные цели, перспектива роста и прозрачные правила; - Масштабируется практика обучения и развития — вы можете сделать её воспроизводимой и измеримой; Ваш стиль человекоцентричности менее эффективен в ситуациях, если: - В приоритете — построение доверительных отношений в команде; - В команде есть напряжение и конфликты; - Команде не хватает неформального общения; - Надо усилить сплоченность. | D13: Попробуйте расширить набор инструментов лидера: сохранить фокус на результатах, процессах и развитии людей, но усилить управляемость через создание доброжелательной и уважительной среды в команде. Для этого: Узнайте больше о своей команде: - Узнайте, достаточно ли в команде уважительного общения и взаимопомощи; - Спросите, есть ли в команде невысказанные конфликты или напряжение; - Проверьте, насколько сотрудники чувствуют себя частью сплочённой команды; - Уточните, достаточно ли в команде неформального общения, эмпатии. Внедряйте в практику и делайте чаще: - Создавайте пространство для открытого, неформального диалога; - В конце встреч уделяйте немного времени, чтобы каждый мог поблагодарить коллегу за помощь, поддержку; - Чаще обсуждайте состояние команды; - Развивайте культуру уважительной и поддерживающей обратной связи; - В сложных ситуациях практикуйте не только чёткий, системный и развивающий, но и эмпатичный разговор. - Уделяйте больше времени созданию сплочённой команды и культуры взаимопомощи. Скорректируйте/ Закрепите изменения и дополните свой стиль: - Развивайте взаимопомощь и поддержку в команде; - Введите правило- обращаться за поомщью, это не слабость, а сила команды; - Организуйте встречи, где сотрудники могут поделиться состоянием и получить обратную связь не только по рабочим задачам, а личную. - Связывайте командное взаимодействие с ценностью для клиента и результатом.
A14: Широкий профиль | B14: Целеустремленный, Командный, Процессный | C14: Сочетение данных стилей объединяет фокус на команду, создание уважительных коммуникаций (командный стиль); организацию отлаженных рабочих процессов (процессный стиль); а также ориентацию на результат и создание ценности для клиентов и Общества (целеустремленный стиль). Векторы в модели человекоцентричности — Стратегия, Культура, Процессы и практики. Приоритеты - достижение измеримых целей через уважительную командную культуру и прозрачные, эффективные процессы. Сильные стороны: - Достижение результатов в атмосфере уважения и порядка в рабочих процессах; - Умение удерживать фокус и выделять приоритеты; - Доброжелательная культура общения; - Уважительная коммуникация и конструктивная обратная связь; - Прозрачность и предсказуемость в работе; - Четкая организация рабочих процессов. Как стиль влияет на человекоцентричную культуру в Ростелекоме: Ваш стиль формирует культуру достижения высоких результатов через уважительные и доброжательные коммуникации в команде; и организацию рабочих процессов, в которых каждый понимает свою зону ответственности и способ действий. Лидер показывает, что достигать результатов можно через чёткие цели и образ результата, понятные правила и создание доверительный командных отношений. Ваш стиль человекоцентричности эффективен в ситуациях, если: - Нужно быстро достичь измеримых результатов, сохранив командный дух и опираясь на чёткие процессы; - Команда работает с разными задачами— вы даёте ясность целей, ролей и процессов, сохраняя уважительную атмосферу; - Возникают риски нарушения сроков — вы оперативно перераспределяете нагрузку, опираясь на чёткие роли и прозрачные договорённости; - Команде нужны одновременно прозрачность, предсказуемость и уважительная, поддерживающая атмосфера. Ваш стиль человекоцентричности менее эффективен в ситуациях, если: - В текущих приоритетах-раскрытие потенциала сотрудников; - Сотрудникам не хватает мотивации и веры в своии возможности; - Нужны инновации, эксперименты и нестандартные решения — ваша склонность к порядку и результату может ограничивать свободу и креативность; - Сотрудникам нужна помощь в построении индивидуальных траекторий развития. | D14: Попробуйте расширить набор инструментов лидера: сохранить фокус на результатах, эффективности процессов, отношениях и культуре, но усилить управляемость через мотивацию и развитие сотрудников. Для этого: Узнайте больше о своей команде: - Узнайте, видят ли сотрудники связь между своей работой и возможностью профессионального и личностного роста; - Узнайте, известны ли сотрудникам их возможности для роста, раскрывают ли они свой потенциал; - Спросите, достаточно ли развивающих задач, которые бросают вызов; - Проверьте, есть ли у сотрудников индивидуальные траектории развития. Внедряйте в практику и делайте чаще: - Давайте сотрудникам задачи на развитие, помогайте им усиливать свои компетенции; - В нестандартных ситуациях делайте пилоты и проводите эксперименты для проверки своих гипотез; - Чаще проводите встречи, посвященные развитию, обмен опытом; - Отмечайте личный рост сотрудников, освоение новых навыков; - Подбирайте инструменты индидуальной мотивации. Для это проводите мотивационные встречи; - Вдохновляйте на развитие своим примеров регулярного обучения. Скорректируйте/ Закрепите изменения и дополните свой стиль: - Развивайте культуру, в которой есть место эксперименту; - Составляйте вместе с сотрудниками их индивидуальные траектории развития компетенций: в чём их сильные стороны, а какие навыки можно усилить; - Вдохновляйте личным примером; - Исследуйте факторы мотивации, значимые для сотрудников вашей команды и мотивируйте.
A15: Широкий профиль | B15: Вдохновляющий, Командный, Процессный | C15: Сочетание данных стилей объединяет фокус на развитие людей, их мотивацию (вдохновляющий стиль); создание доброжательной, уважительной командной атмосферы (командный стиль) и организацию прозрачных рабочих процессов (процессный стиль). Приоритеты - создание развивающей, поддерживающей и хорошо организованной среды, в которой люди чувствуют уважение, видят перспективы роста и опираются на понятные, эффективные процессы. В модели человекоцентричности такому стилю соответствуют три вектора: «Лидер», «Культура» и «Процессы и практики». Сильные стороны: - Создание условий для раскрытия потенциала сотрудников; - Возможности для роста и обучения; - Доброжелательная культура общения; - Уважительная коммуникация и конструктивная обратная связь; - Прозрачность и предсказуемость в работе; - Устранение организационных барьеров; Как стиль влияет на человекоцентричную культуру в Ростелекоме: Ваш стиль создает культуру, в которой каждый видит перспективу роста и получает поддержку в развитии; сотрудники чувствуют уважение, доверие и готовность помочь; люди понимают свою роль, зоны ответственности и правила взаимодействия; а рабочие процессы выстраиваются четко и прозрачно. Ваш стиль человекоцентричности эффективен в ситуациях, если: - Команде нужно одновременно создать атмосферу доверия, выстроить систему развития и наладить прозрачные процессы; - Формируется новая команда — вы закладываете и культуру наставничества, и уважительное общение, и понятные процессы; - Необходимо адаптировать и развивать новых сотрудников; - Масштабируется типовая работа и важно сохранить человеческое отношение. Ваш стиль человекоцентричности менее эффективен, если: - Команда находится в условиях жёстких сроков и ограниченных ресурсов; - Нужно принять быстрое решение, не вовлекая при этом команду в обсуждение; - Требуется достижение высоких результатов в условиях неопреденности или кризиса. | D15: Попробуйте расширить набор инструментов лидера: сохранить фокус на команде, развитии и организации процессов, но усилить управляемость через ясные цели, измеримые результаты и эффективные действия в условиях неопределенности. Для этого: Узнайте больше о своей команде: - Спросите, понимает ли команда, какую ценность для клиента и компании создаёт их работа; - Проясните, понятны ли общие цели и образ результата, ответьте на вопросы сотрудников; - Узнайте, достаточно ли ясности приоритетов, сроков и измеримых критериев успеха; - Проверьте, насколько быстро команда способна принимать решения в условиях жёстких сроков и неопределённости Внедряйте в практику и делайте чаще: - На встречах больше обсуждайте, «какую ценность для клиента мы создаём»; - Фиксируйте решения письменно: кто, что, к какому сроку выполняет; - В сложных ситуациях практикуйте не только уважительный, но и прямой разговор; - В ситуациях жёстких сроков старайтесь не затягивать принятие решений. Скорректируйте/ Закрепите изменения и дополните свой стиль: - Четко формулируйте цели и контролируйте достижение результата; - Всегда сверяйтесь: создают ли ваши решения ценность для клиента и компании; - Развивайте навыки управления командой в кризисных ситуациях и условиях неопределенности.
A16: Сбалансированный профиль | B16: Целеустремленный, Вдохновляющий, Командный и Процессный | C16: Ваш профиль объединяет все четыре стиля человекоцентричного лидерства: целеустремленный, процессный, вдохновляющий и командный. Векторы в модели человекоцентричности: Стратегия, Процессы и практики, Лидер и Культура. Приоритеты лидера- гармоничное сочетание результата, отношений, развития и порядка. Лидер ставит амбициозные цели, поддерживает команду, развивает людей и выстраивает эффективные процессы. Сильные стороны - Универсальность и адаптивность; - Гибкая реакция на изменения; - Формирование целостной человекоцентричной культуры; - Системное видение: лидер видит, как цели, отношения, развитие и процессы влияют друг на друга, и может выстраивать сбалансированные решения. Как стиль влияет на человекоцентричную культуру в Ростелекоме? Ваш стиль создает культуру, в которой: - Цели понятны и связаны с пользой для клиента; - Команда чувствует уважение, поддержку и командый дух; - Сотрудники видят перспективы роста и получают задачи для развития; - Работа организована прозрачно, предсказуемо и без лишних барьеров (Процессный). Ваш стиль человекоцентричности эффективен в ситуациях, если: - Ситуация требует комплексного подхода; - От лидера требуется проявление гибкости; - Вы управляете разными задачами и разными командами; - Команда находится на этапе своего роста. Ваш стиль человекоцентричности менее эффективен, если: - нужен ярко выраженный стиль, а не баланс (например, в кризисной ситуации жёсткого достижения целей или в глубокой процессной трансформации); - требуется действовать в условиях жесткой конкуренции и радикального сокращения издержек; - нужно быстро сделать принципиальный выбор, в котором сложно найти баланс (например, между долгосрочным развитием и краткосрочной прибылью). | D16: Ваш стиль человекоцентричности сбалансированный. Это означает, что все стили проявлены равномерно, отсутствуют ключевые зоны роста. Однако, чтобы усилить ваш стиль, попробуйте выстроить стратегию развития в двух направлениях (продолжать капитализировать сильные стороны): - Углубление осознанности — чтобы вы могли ещё точнее выбирать нужный стиль под конкретную ситуацию. - Усиление гибкости и «переключения» — чтобы вы могли быть ещё более эффективным, используя сильные стороны каждого стиля осознанно и вовремя. Узнайте больше о своей команде: Чтобы понять, какие стили требуют большего внимания в текущей ситуации, соберите обратную связь по всем четырём стилям: -Есть ли чёткое понимание приоритетов, сроков и измеримых результатов; - Достаточно ли в команде уважительного общения и взаимопомощи; - Видят ли сотрудники возможности для роста, получают ли они достаточно развивающих задач, бросающих им вызов; - Есть ли «узкие места» или лишние барьеры, которые мешают эффективно работать? Внедряйте в практику и делайте чаще: Рекомендуем развивать осознанное переключение между стилями и глубину в каждом из них, когда это необходимо. - Перед важной встречей, проектом или решением задавайте себе вопрос: «Какой стиль сейчас нужен в первую очередь?» - В начале работы с задачей определите, какой аспект сейчас в приоритете. Например: - Если горят сроки, нужны быстрые решения и четкие KPI, применяйте Целеустремленный стиль; - Если в команде нужно выстроить уважительный диалог, восстановить доверие, применяйте Командный стиль; - Если люди потеряли мотивацию, требуется выстроить индивидуальные треки развития — применяйте Вдохновляющий стиль; - Если нужно оптимизировать рабочие процессы и создать порядок — применяйте Процессный стиль. - В ситуациях, когда сложно сохранять баланс, делайте оправданный выбор в пользу одного стиля, например, когда нужно быстро принять сложное кадровое решение (в ущерб командному стилю), ради достижения результата (в пользу целеустремленного стиля). Закрепите изменения и дополните свой стиль:. Продолжайте укреплять свои сильные стороны- - Делайте связку: как текущие задачи способствуют созданию ценности для клиентов и Общества; - Упростите правила взаимодействия чёткими договорённостями зон ответственности, ролей, сроков выполнения задач; - Поддерживайте уважительный и доброжелательный тон общения в команде; - Оптимизируйте рабочие процессы, делая их более прозрачными и простыми; - Связывайте развитие людей с реальными бизнес-задачами и пользой для клиента; - Регулярно сверяйтесь, какой стиль сейчас нужен — и осознанно переключайтесь.

Sheet Прототип отчета
B1: Отчёт по тесту «Определение ведущего стиля человекоцентричного лидерства»
B4: Об отчёте
B5: ='[1]Вводная часть отчета'!A2 -> Готово! Мы всё посчитали, ваш результат ниже. Отчёт отображает результаты самодиагностики, полученные при прохождении теста. Ваш отчёт состоит из нескольких блоков: - Введение - Результаты - Характеристика других стилей - Рекомендации по развитию вашего стиля человекоцентричного лидерства
B13: Об инструменте
B14: ='[1]Вводная часть отчета'!A4 -> Инструмент «Тест на определение ведущего стиля человекоцентричного лидерства» помогает понять, как вы создаёте осмысленную, тёплую и результативную рабочую среду для людей в вашей команде. Тест построен на базе: - Модели человекоцентричного лидерства в "Ростелекоме" - Классической двухфакторой модели руководства Ренсиса Лайкерта ("Фокус на людей" и "Фокус на задачи") - Теории контекстов взаимодействия в команде Рэймонда Белбина Человекоцентричное лидерство — это подход к управлению, где в центре решений и внимания лидера всегда находится человек: сотрудник, коллега, клиент, партнёр. Модель человекоцентричного лидерства опирается на четыре вектора: Культура, Лидер, Процессы и практики, Стратегия, и каждому вектору соответствует свой стиль лидерства. Важно: тест не измеряет «уровень» или «индекс» человекоцентричности и не даёт оценочного вердикта. Его задача — помочь лидеру лучше понять особенности своего стиля управления и увидеть, в каких ситуациях этот стиль наиболее эффективен, а где полезно подключать другие подходы.
B24: Ваши результаты: | M24: Если 1 стиль "Ваш ведущий стиль…" Если 2 стиля "У вас наиболее выражены два стиля:…" Если 3 стиля "Увас наиболее выражены три стиля" Если 4 стиля "Ваш профиль сбалансирован и сочетает 4 стиля:…"
B25: 🎯 Целеустремленный | D25: ✨ Вдохновляющий | F25: 🤝 Командный | H25: ⚙️ Процессный | K25: 🎯 Целеустремленный | L25: ✨ Вдохновляющий
K26: ='[1]Механика подсчета результатов'!$T$3 -> 39 | L26: ='[1]Механика подсчета результатов'!$U$3 -> 9
B29: У вас наиболее выражены два стиля: целеустремленный и процессный
B30: Описание ваших результатов
B53: Как мне повысить человекоцентричность в моей команде?
B81: =IF('[1]Механика подсчета результатов'!$AA$3=4,"","Ознакомьтесь с другими стилями") -> Ознакомьтесь с другими стилями | M81: Изменения после пилота: 1.если сбалансированный - ознакомьтесь с полным описанием ведущим стилей или не выводим этот раздел? 2.если двухвекторный или широкий- ознакомьтесь с другими стилям (выводим 2 оставшихся или 1 оставшийся в зависимости от результатов) 3.если результат с ведущий стилем- выводим 3 стиля, менее характерных для участника- ознакомьтесь с другими стилями Стили выводятся по убыванию.
B94: =IF(OR('[1]Механика подсчета результатов'!$AA$3=4,3>(4-'[1]Механика подсчета результатов'!$AA$3)),"",'[1]Механика подсчета результатов'!$AW$3)
B101: =IF(OR('[1]Механика подсчета результатов'!$AA$3=4,3>(4-'[1]Механика подсчета результатов'!$AA$3)),"",'[1]Механика подсчета результатов'!$AW$3)
